Workbook

Sheet Daily Data
A1: Date | B1: Orders | C1: Revenue | D1: Add-ons | E1: Total Sales | F1: Expenses | G1: Net Profit | H1: Best Seller | I1: Issue | J1: Peak Hour
A2: Jan 01 | B2: 33 | C2: 1980 | D2: 60 | E2: 2040 | F2: 189 | G2: 1851 | H2: Tagapagmana | I2: None | J2: 6–8 PM
A3: Jan 02 | B3: 41 | C3: 3444 | D3: 80 | E3: 3524 | F3: 40 | G3: 3484 | H3: Nakakaluwag | I3: None | J3: 4–6 PM
A4: Jan 03 | B4: 37 | C4: 4033 | D4: 0 | E4: 4033 | F4: 112 | G4: 3921 | H4: Rich Kid | I4: None | J4: 5–7 PM
A5: Jan 04 | B5: 24 | C5: 2160 | D5: 0 | E5: 2160 | F5: 70 | G5: 2090 | H5: Contractor | I5: Delivery delay | J5: 5–7 PM
A6: Jan 05 | B6: 18 | C6: 2124 | D6: 150 | E6: 2274 | F6: 60 | G6: 2214 | H6: Nakakaluwag | I6: None | J6: 6–8 PM
A7: Jan 06 | B7: 43 | C7: 5074 | D7: 60 | E7: 5134 | F7: 50 | G7: 5084 | H7: Nakakaluwag | I7: None | J7: 6–9 PM
A8: Jan 07 | B8: 29 | C8: 3335 | D8: 0 | E8: 3335 | F8: 60 | G8: 3275 | H8: Rich Kid | I8: Short packs | J8: 7–9 PM
A9: Jan 08 | B9: 33 | C9: 3564 | D9: 150 | E9: 3714 | F9: 70 | G9: 3644 | H9: Contractor | I9: None | J9: 7–9 PM
A10: Jan 09 | B10: 43 | C10: 3569 | D10: 40 | E10: 3609 | F10: 150 | G10: 3459 | H10: Nakakaluwag | I10: None | J10: 7–9 PM
A11: Jan 10 | B11: 29 | C11: 1856 | D11: 80 | E11: 1936 | F11: 70 | G11: 1866 | H11: Nakakaluwag | I11: None | J11: 6–8 PM
A12: Jan 11 | B12: 32 | C12: 3008 | D12: 150 | E12: 3158 | F12: 60 | G12: 3098 | H12: Nakakaluwag | I12: None | J12: 5–7 PM
A13: Jan 12 | B13: 17 | C13: 1326 | D13: 80 | E13: 1406 | F13: 20 | G13: 1386 | H13: Rich Kid | I13: None | J13: 6–9 PM
... A60: Feb 28 | B60: 17 | C60: 1326 | D60: 100 | E60: 1426 | F60: 70 | G60: 1356 | H60: Nakakaluwag | I60: None | J60: 5–7 PM

Sheet Analytics
A1: Metric | B1: Value
A2: Total Revenue | B2: =SUM('Daily Data'!E2:E60) -> 154016
A3: Total Expenses | B3: =SUM('Daily Data'!F2:F60) -> 3446
A4: Total Profit | B4: =SUM('Daily Data'!G2:G60) -> 150570
A5: Average Daily Sales | B5: =AVERAGE('Daily Data'!E2:E60) -> 2610.4407

Sheet Monthly Summary
A1: Metric | B1: January | C1: February
A2: Total Sales | B2: =SUM('Daily Data'!E2:E32) -> 87467 | C2: =SUM('Daily Data'!E33:E60) -> 66549
A3: Total Expenses | B3: =SUM('Daily Data'!F2:F32) -> 2084 | C3: =SUM('Daily Data'!F33:F60) -> 1362
A4: Net Profit | B4: =SUM('Daily Data'!G2:G32) -> 85383 | C4: =SUM('Daily Data'!G33:G60) -> 65187
A5: Average Daily Sales | B5: =AVERAGE('Daily Data'!E2:E32) -> 2821.5161 | C5: =AVERAGE('Daily Data'!E33:E60) -> 2376.75

Sheet Product Analytics
A1: Product | B1: Frequency
A2: Poorita | B2: =COUNTIF('Daily Data'!H2:H60,"Poorita") -> 7
A3: Nakakaluwag | B3: =COUNTIF('Daily Data'!H2:H60,"Nakakaluwag") -> 19
A4: Contractor | B4: =COUNTIF('Daily Data'!H2:H60,"Contractor") -> 6
A5: Rich Kid | B5: =COUNTIF('Daily Data'!H2:H60,"Rich Kid") -> 13
A6: Tagapagmana | B6: =COUNTIF('Daily Data'!H2:H60,"Tagapagmana") -> 14

Sheet Issue Analytics
A1: Issue | B1: Frequency
A2: None | B2: =COUNTIF('Daily Data'!I2:I60,"None") -> 48
A3: Short packs | B3: =COUNTIF('Daily Data'!I2:I60,"Short packs") -> 4
A4: Low sales | B4: =COUNTIF('Daily Data'!I2:I60,"Low sales") -> 3
A5: Missing stock | B5: =COUNTIF('Daily Data'!I2:I60,"Missing stock") -> 2
A6: High expenses | B6: =COUNTIF('Daily Data'!I2:I60,"High expenses") -> 1
A7: Delivery delay | B7: =COUNTIF('Daily Data'!I2:I60,"Delivery delay") -> 1
